app.py
commit5-0.1.1.dist-info/entry_points.txt
commit5-0.1.1.dist-info/WHEEL
commit5-0.1.1.dist-info/METADATA
commit5-0.1.1.dist-info/RECORD
