Metadata-Version: 2.1
Name: commit5
Version: 0.1.1
Summary: Locally generate commit messages using CodeTrans and FastT5
Author-email: Kevin Lu <kevinlu1248@gmail.com>
Requires-Dist: docker
Requires-Dist: typer
Requires-Dist: requests
Requires-Dist: pytest ; extra == "dev"
Requires-Dist: flit ; extra == "dev"
Requires-Dist: twine ; extra == "dev"
Provides-Extra: dev
